{
  "timestamp" : "2025-11-30T02:05:54Z",
  "count_outdated" : 539,
  "uniques_outdated" : 93,
  "count" : 541,
  "uniques" : 95,
  "views" : [
    {
      "timestamp": "2025-11-26T00:00:00Z",
      "count": 1,
      "count_minmax": [ 1, 1 ],
      "count_decinc": [ 0, 1 ],
      "uniques": 1,
      "uniques_minmax": [ 1, 1 ],
      "uniques_decinc": [ 0, 1 ]
    },
    {
      "timestamp": "2025-11-29T00:00:00Z",
      "count": 1,
      "count_minmax": [ 1, 1 ],
      "count_decinc": [ 0, 1 ],
      "uniques": 1,
      "uniques_minmax": [ 1, 1 ],
      "uniques_decinc": [ 0, 1 ]
    }
  ]
}
